scienceio/__init__.py
cnco-0.0.0.dist-info/METADATA
cnco-0.0.0.dist-info/WHEEL
cnco-0.0.0.dist-info/top_level.txt
cnco-0.0.0.dist-info/RECORD
