Metadata-Version: 2.1
Name: cnco
Version: 0.0.0
Summary: cnco python client
Home-page: https://github.com/hizvi
Author: cnco
Author-email: hasangr8@gmail.com
License: UNKNOWN
Platform: UNKNOWN
Classifier: Programming Language :: Python :: 3
